Metadata-Version: 2.1
Name: mkdocs-techdocs-redirects
Version: 0.1.1
Summary: A MkDocs plugin to redirect old links to new addresses for TechDocs.
Home-page: https://github.com/matchaxnb/mkdocs-techdocs-redirects
Author: Macha Desoutter
Author-email: matchaxnb@proton.me
License: MIT
Keywords: mkdocs redirect techdocs
Platform: UNKNOWN
Classifier: Development Status :: 4 - Beta
Classifier: Intended Audience :: Developers
Classifier: Intended Audience :: Information Technology
Classifier: License :: OSI Approved :: MIT License
Classifier: Programming Language :: Python
Classifier: Programming Language :: Python :: 3
Classifier: Programming Language :: Python :: 3.6
Classifier: Programming Language :: Python :: 3.7
Classifier: Programming Language :: Python :: 3.8
Classifier: Programming Language :: Python :: 3.9
Classifier: Programming Language :: Python :: 3.10
Requires-Python: >=3.6
Provides-Extra: dev
Provides-Extra: test
Provides-Extra: release
License-File: LICENSE
